backlog/__init__.py
backlog/backlog.py
backlog/setup.py
backlog_restlib.egg-info/PKG-INFO
backlog_restlib.egg-info/SOURCES.txt
backlog_restlib.egg-info/dependency_links.txt
backlog_restlib.egg-info/requires.txt
backlog_restlib.egg-info/top_level.txt