Metadata-Version: 1.0
Name: backlog-restlib
Version: 0.0.1
Summary: thin wrapper for Backlog API v2.
Home-page: UNKNOWN
Author: kitsu yui
Author-email: yui.kitsu+git@gmail.com
License: UNKNOWN
Platform: UNKNOWN
